context/Context.py
context/__init__.py
context/code_generator.py
context/config.py
context/file_manager.py
context/log.py
context/openai_interface.py
context/tag_parser.py
ContextLang-0.1.55.dist-info/LICENSE
ContextLang-0.1.55.dist-info/METADATA
ContextLang-0.1.55.dist-info/WHEEL
ContextLang-0.1.55.dist-info/entry_points.txt
ContextLang-0.1.55.dist-info/top_level.txt
ContextLang-0.1.55.dist-info/RECORD
