Metadata-Version: 2.1
Name: ContextLang
Version: 0.1.55
Summary: Cross-platform, AI code generator CLI tool and ContexLang preprocessor
Home-page: https://github.com/werfish/Context-Lang
Author: Robert Mazurowski
Author-email: werfish1@gmail.com
License: Apache 2.0
Project-URL: Documentation, https://github.com/werfish/Context-Lang
Project-URL: Source, https://github.com/werfish/Context-Lang
Project-URL: Tracker, https://github.com/werfish/Context-Lang/issues
Classifier: Development Status :: 2 - Pre-Alpha
Classifier: Environment :: Win32 (MS Windows)
Classifier: Intended Audience :: Developers
Classifier: License :: OSI Approved :: Apache Software License
Classifier: Operating System :: Microsoft :: Windows :: Windows 10
Classifier: Programming Language :: Python :: 3.11
Classifier: Programming Language :: Assembly
Classifier: Programming Language :: Basic
Classifier: Programming Language :: C
Classifier: Programming Language :: C#
Classifier: Programming Language :: C++
Classifier: Programming Language :: Cython
Classifier: Programming Language :: Java
Classifier: Programming Language :: JavaScript
Classifier: Programming Language :: Kotlin
Classifier: Programming Language :: Lisp
Classifier: Programming Language :: Objective C
Classifier: Programming Language :: PHP
Classifier: Programming Language :: PL/SQL
Classifier: Programming Language :: R
Classifier: Programming Language :: Rust
Classifier: Programming Language :: SQL
Classifier: Programming Language :: Visual Basic
Classifier: Topic :: Software Development :: Code Generators
Classifier: Topic :: Software Development :: Pre-processors
License-File: LICENSE
Requires-Dist: requests <3.0.0,>=2.24.0
Requires-Dist: python-dotenv <0.20.0,>=0.15.0
Requires-Dist: openai ==1.14.3
Requires-Dist: tenacity <7.0.0,>=6.3.1
Requires-Dist: colorama <1.0.0,>=0.4.3
Requires-Dist: gitignore-parser ==0.1.11
